{
    "Samsung": {
        "ticker": "005930.KS",
        "avg_price": 75000,
        "deposit": 1500000
    },
    "TIGER 미국우주테크": {
        "ticker": "465540.KS",
        "avg_price": 13534.0,
        "deposit": 43132858.0
    },
    "ACE AI반도체TOP3+": {
        "ticker": "471370.KS",
        "avg_price": 73852.0,
        "deposit": 52287216.0
    },
    "RISE AI전력인프라": {
        "ticker": "482810.KS",
        "avg_price": 22569.0,
        "deposit": 49516386.0
    },
    "KODEX AI반도체TOP2플러스": {
        "ticker": "471540.KS",
        "avg_price": 57568.0,
        "deposit": 46054400.0
    },
    "TIGER 2차전지TOP10": {
        "ticker": "385530.KS",
        "avg_price": 11795.0,
        "deposit": 7077000.0
    },
    "KoAct 글로벌양자컴퓨팅액티브": {
        "ticker": "472140.KS",
        "avg_price": 30773.0,
        "deposit": 6308465.0
    },
    "가온전선": {
        "ticker": "000500.KS",
        "avg_price": 331490.0,
        "deposit": 660300.0
    },
    "SK하이닉스": {
        "ticker": "000660.KS",
        "avg_price": 2757876.0,
        "deposit": 5493790.0
    },
    "삼성전자": {
        "ticker": "005930.KS",
        "avg_price": 309402.0,
        "deposit": 923989.0
    },
    "삼성전기우": {
        "ticker": "009155.KS",
        "avg_price": 778741.0,
        "deposit": 775527.0
    },
    "LS ELECTRIC": {
        "ticker": "010120.KS",
        "avg_price": 255278.0,
        "deposit": 2033994.0
    }
}